odoo/addons/sale_order_report_without_price/README.rst
odoo/addons/sale_order_report_without_price/__init__.py
odoo/addons/sale_order_report_without_price/__manifest__.py
odoo/addons/sale_order_report_without_price/i18n/it.po
odoo/addons/sale_order_report_without_price/i18n/sale_order_report_without_price.pot
odoo/addons/sale_order_report_without_price/readme/CONTRIBUTORS.md
odoo/addons/sale_order_report_without_price/readme/DESCRIPTION.md
odoo/addons/sale_order_report_without_price/readme/USAGE.md
odoo/addons/sale_order_report_without_price/report/sale_report.xml
odoo/addons/sale_order_report_without_price/report/sale_report_templates.xml
odoo/addons/sale_order_report_without_price/static/description/icon.png
odoo/addons/sale_order_report_without_price/static/description/index.html
odoo_addon_sale_order_report_without_price-18.0.1.0.0.2.dist-info/METADATA
odoo_addon_sale_order_report_without_price-18.0.1.0.0.2.dist-info/WHEEL
odoo_addon_sale_order_report_without_price-18.0.1.0.0.2.dist-info/top_level.txt
odoo_addon_sale_order_report_without_price-18.0.1.0.0.2.dist-info/RECORD
