Metadata-Version: 2.1
Name: odoo-addon-sale_order_report_without_price
Version: 18.0.1.0.0.2
Requires-Python: >=3.10
Requires-Dist: odoo==18.0.*
Summary: Allow you to generate quotation and order reports without price.
Home-page: https://github.com/OCA/sale-workflow
License: LGPL-3
Author: Akretion, Open Source Integrators, Odoo Community Association (OCA)
Author-email: support@odoo-community.org
Classifier: Programming Language :: Python
Classifier: Framework :: Odoo
Classifier: Framework :: Odoo :: 18.0
Classifier: License :: OSI Approved :: GNU Lesser General Public License v3 (LGPLv3)
